{
  "id": "button_row",
  "type": "SharedSlice",
  "name": "ButtonRow",
  "description": "ButtonRow",
  "variations": [
    {
      "id": "default",
      "name": "Default",
      "docURL": "...",
      "version": "sktwi1xtmkfgx8626",
      "description": "ButtonRow",
      "primary": {},
      "items": {
        "buttonText": {
          "config": {
            "label": "Button Text",
            "placeholder": ""
          },
          "type": "Text"
        },
        "buttonLink": {
          "config": {
            "label": "Button Link",
            "placeholder": "",
            "allowTargetBlank": false
          },
          "type": "Link"
        }
      }
    }
  ]
}